condacolab.py
condacolab-0.1.8.dist-info/LICENSE
condacolab-0.1.8.dist-info/WHEEL
condacolab-0.1.8.dist-info/METADATA
condacolab-0.1.8.dist-info/RECORD
