Metadata-Version: 2.1
Name: condacolab
Version: 0.1.8
Summary: Install Conda and friends on Google Colab, easily
Home-page: https://github.com/jaimergp/condacolab
License: MIT
Author: Jaime Rodríguez-Guerra
Author-email: jaimergp@users.noreply.github.com
Requires-Python: >=3.10,<4.0
Classifier: License :: OSI Approved :: MIT License
Classifier: Programming Language :: Python :: 3
Project-URL: Repository, https://github.com/jaimergp/condacolab
